{
  "lines": [
    [
      [0, 5],
      [1, 20],
      [2, 45],
      [3, 110],
      [4, 165],
      [5, 200],
      [6, 235],
      [7, 209],
      [8, 276],
      [9, 278],
      [10, 279],
      [11, 268],
      [12, 250],
      [13, 243],
      [14, 257],
      [15, 259],
      [16, 251],
      [17, 250],
      [18, 255],
      [19, 262],
      [20, 260],
      [21, 270],
      [22, 300],
      [23, 305]
    ],
    [
      [0, 10],
      [1, 30],
      [2, 50],
      [3, 120],
      [4, 175],
      [5, 210],
      [6, 245],
      [7, 219],
      [8, 286],
      [9, 288],
      [10, 290],
      [11, 278],
      [12, 260],
      [13, 253],
      [14, 267],
      [15, 269],
      [16, 261],
      [17, 260],
      [18, 265],
      [19, 272],
      [20, 270],
      [21, 280],
      [22, 310],
      [23, 315]
    ]
  ],
  "areas": [
    {
      "highLine": [
        [0, 40],
        [1, 80],
        [2, 89],
        [3, 180],
        [4, 257],
        [5, 290],
        [6, 345],
        [7, 299],
        [8, 346],
        [9, 358],
        [10, 349],
        [11, 328],
        [12, 350],
        [13, 343],
        [14, 347],
        [15, 349],
        [16, 341],
        [17, 340],
        [18, 340],
        [19, 342],
        [20, 360],
        [21, 400],
        [22, 430],
        [23, 455]
      ],
      "lowLine": [
        [0, 20],
        [1, 35],
        [2, 43],
        [3, 70],
        [4, 95],
        [5, 90],
        [6, 125],
        [7, 139],
        [8, 166],
        [9, 168],
        [10, 189],
        [11, 198],
        [12, 190],
        [13, 193],
        [14, 197],
        [15, 239],
        [16, 251],
        [17, 190],
        [18, 195],
        [19, 192],
        [20, 190],
        [21, 193],
        [22, 192],
        [23, 225]
      ]
    },
    {
      "highLine": [
        [0, 20],
        [1, 50],
        [2, 79],
        [3, 150],
        [4, 257],
        [5, 280],
        [6, 325],
        [7, 279],
        [8, 326],
        [9, 338],
        [10, 329],
        [11, 308],
        [12, 310],
        [13, 323],
        [14, 327],
        [15, 329],
        [16, 321],
        [17, 320],
        [18, 320],
        [19, 322],
        [20, 360],
        [21, 410],
        [22, 410],
        [23, 415]
      ],
      "lowLine": [
        [0, 5],
        [1, 10],
        [2, 18],
        [3, 55],
        [4, 70],
        [5, 75],
        [6, 86],
        [7, 100],
        [8, 128],
        [9, 140],
        [10, 152],
        [11, 170],
        [12, 174],
        [13, 177],
        [14, 179],
        [15, 195],
        [16, 197],
        [17, 177],
        [18, 179],
        [19, 178],
        [20, 180],
        [21, 187],
        [22, 187],
        [23, 201]
      ]
    }
  ],
  "scatter": [
    [2, 50],
    [4, 150],
    [6, 13],
    [6, 50],
    [7, 65],
    [13, 70]
  ]

}
